pvb_hashev/__init__.py
pvb_hashev/gitlab_client.py
pvb_hashev/google_client.py
pvb_hashev/logger.py
pvb_hashev/sync.py
pvb_hashev-0.1.3.dist-info/licenses/LICENSE
pvb_hashev-0.1.3.dist-info/METADATA
pvb_hashev-0.1.3.dist-info/WHEEL
pvb_hashev-0.1.3.dist-info/top_level.txt
pvb_hashev-0.1.3.dist-info/RECORD
