Metadata-Version: 2.4
Name: pvb-hashev
Version: 0.1.3
Summary: Google sheets with gitlab sync
Author-email: xottab-ops <jassik2002@mail.ru>
License: MIT License
Project-URL: Source, https://github.com/xottab-ops/google-sheets-to-gitlab-markdown
Keywords: google-sheets,gitlab,synchronization,markdown,automation,data-export,sync-service
Classifier: Development Status :: 3 - Alpha
Classifier: Intended Audience :: Developers
Classifier: Topic :: Software Development :: Libraries
Classifier: Topic :: Utilities
Classifier: License :: OSI Approved :: MIT License
Classifier: Programming Language :: Python :: 3
Classifier: Programming Language :: Python :: 3.13
Classifier: Operating System :: OS Independent
Requires-Python: <3.14,>=3.13
License-File: LICENSE
Requires-Dist: gspread==6.1.4
Requires-Dist: google-auth==2.35.0
Requires-Dist: google-api-python-client==2.149.0
Requires-Dist: google-auth-httplib2==0.2.0
Requires-Dist: google-auth-oauthlib==1.2.1
Requires-Dist: pandas==2.2.3
Requires-Dist: tabulate==0.9.0
Requires-Dist: python-gitlab==4.13.0
Dynamic: license-file
